efficientnet_lite1_pytorch_model/__init__.py
efficientnet_lite1_pytorch_model/models/.gitignore
efficientnet_lite1_pytorch_model/models/efficientnet-lite1-77cc7160.pth
efficientnet_lite1_pytorch_model-0.1.0.dist-info/LICENSE
efficientnet_lite1_pytorch_model-0.1.0.dist-info/METADATA
efficientnet_lite1_pytorch_model-0.1.0.dist-info/WHEEL
efficientnet_lite1_pytorch_model-0.1.0.dist-info/top_level.txt
efficientnet_lite1_pytorch_model-0.1.0.dist-info/RECORD
